detpy/__init__.py
detpy/DETAlgs/__init__.py
detpy/DETAlgs/aade.py
detpy/DETAlgs/al_shade.py
detpy/DETAlgs/base.py
detpy/DETAlgs/comde.py
detpy/DETAlgs/de.py
detpy/DETAlgs/degl.py
detpy/DETAlgs/delb.py
detpy/DETAlgs/derl.py
detpy/DETAlgs/detcr.py
detpy/DETAlgs/eide.py
detpy/DETAlgs/emde.py
detpy/DETAlgs/eps_ade.py
detpy/DETAlgs/eps_de.py
detpy/DETAlgs/eps_de_w_dc.py
detpy/DETAlgs/eps_deag.py
detpy/DETAlgs/eps_deg.py
detpy/DETAlgs/eps_rde.py
detpy/DETAlgs/fiade.py
detpy/DETAlgs/ide.py
detpy/DETAlgs/improved_de.py
detpy/DETAlgs/jade.py
detpy/DETAlgs/lshade.py
detpy/DETAlgs/lshade_epsin.py
detpy/DETAlgs/lshadersp.py
detpy/DETAlgs/mgde.py
detpy/DETAlgs/nmde.py
detpy/DETAlgs/opposition_based.py
detpy/DETAlgs/sade.py
detpy/DETAlgs/shade.py
detpy/DETAlgs/shade_1_1.py
detpy/DETAlgs/sps_lshade_eig.py
detpy/DETAlgs/archive_reduction/__init__.py
detpy/DETAlgs/archive_reduction/archive_reduction.py
detpy/DETAlgs/crossover_methods/__init__.py
detpy/DETAlgs/crossover_methods/binomial_crossover.py
detpy/DETAlgs/data/__init__.py
detpy/DETAlgs/data/alg_data.py
detpy/DETAlgs/math/__init__.py
detpy/DETAlgs/math/math_functions.py
detpy/DETAlgs/methods/__init__.py
detpy/DETAlgs/methods/methods_aade.py
detpy/DETAlgs/methods/methods_comde.py
detpy/DETAlgs/methods/methods_de.py
detpy/DETAlgs/methods/methods_degl.py
detpy/DETAlgs/methods/methods_delb.py
detpy/DETAlgs/methods/methods_derl.py
detpy/DETAlgs/methods/methods_eide.py
detpy/DETAlgs/methods/methods_emde.py
detpy/DETAlgs/methods/methods_eps_ade.py
detpy/DETAlgs/methods/methods_eps_de.py
detpy/DETAlgs/methods/methods_eps_de_w_dc.py
detpy/DETAlgs/methods/methods_eps_deag.py
detpy/DETAlgs/methods/methods_eps_deg.py
detpy/DETAlgs/methods/methods_eps_rde.py
detpy/DETAlgs/methods/methods_fiade.py
detpy/DETAlgs/methods/methods_ide.py
detpy/DETAlgs/methods/methods_improved_de.py
detpy/DETAlgs/methods/methods_jade.py
detpy/DETAlgs/methods/methods_lshadersp.py
detpy/DETAlgs/methods/methods_mgde.py
detpy/DETAlgs/methods/methods_nmde.py
detpy-2.0.0.dist-info/licenses/LICENSE
detpy-2.0.0.dist-info/METADATA
detpy-2.0.0.dist-info/WHEEL
detpy-2.0.0.dist-info/top_level.txt
detpy-2.0.0.dist-info/RECORD
